scidatetime/DateTimeParser.py
scidatetime/MdlDateTime.py
scidatetime/__init__.py
scidatetime/__version__.py
scidatetime/dateutil/__init__.py
scidatetime/dateutil/__init__.pyi
scidatetime/dateutil/_common.py
scidatetime/dateutil/_common.pyi
scidatetime/dateutil/_version.py
scidatetime/dateutil/easter.py
scidatetime/dateutil/easter.pyi
scidatetime/dateutil/relativedelta.py
scidatetime/dateutil/relativedelta.pyi
scidatetime/dateutil/rrule.py
scidatetime/dateutil/rrule.pyi
scidatetime/dateutil/tzwin.py
scidatetime/dateutil/utils.py
scidatetime/dateutil/utils.pyi
scidatetime/dateutil/parser/__init__.py
scidatetime/dateutil/parser/__init__.pyi
scidatetime/dateutil/parser/_parser.py
scidatetime/dateutil/parser/isoparser.py
scidatetime/dateutil/parser/isoparser.pyi
scidatetime/dateutil/tz/__init__.py
scidatetime/dateutil/tz/__init__.pyi
scidatetime/dateutil/tz/_common.py
scidatetime/dateutil/tz/_common.pyi
scidatetime/dateutil/tz/_factories.py
scidatetime/dateutil/tz/tz.py
scidatetime/dateutil/tz/tz.pyi
scidatetime/dateutil/tz/win.py
scidatetime/dateutil/zoneinfo/__init__.py
scidatetime/dateutil/zoneinfo/rebuild.py
scidatetime-1.20.5.dist-info/LICENSE
scidatetime-1.20.5.dist-info/METADATA
scidatetime-1.20.5.dist-info/WHEEL
scidatetime-1.20.5.dist-info/top_level.txt
scidatetime-1.20.5.dist-info/RECORD
